pathlib3/__init__.py
pathlib3/__version__.py
pathlib3/py.typed
pathlib3-1.0.14.dist-info/METADATA
pathlib3-1.0.14.dist-info/WHEEL
pathlib3-1.0.14.dist-info/top_level.txt
pathlib3-1.0.14.dist-info/RECORD
