Metadata-Version: 2.4
Name: pathlib3
Version: 1.0.14
Summary: Extended pathlib with 40+ additional utility methods
Home-page: https://github.com/cumulus13/pathlib3
Author: Hadi Cahyadi
Author-email: Hadi Cahyadi <cumulus13@gmail.com>
Maintainer-email: Hadi Cahyadi <cumulus13@gmail.com>
License: MIT License
Project-URL: Homepage, https://github.com/cumulus13/pathlib3
Project-URL: Documentation, https://pathlib3.readthedocs.io
Project-URL: Repository, https://github.com/cumulus13/pathlib3.git
Project-URL: Issues, https://github.com/cumulus13/pathlib3/issues
Project-URL: Changelog, https://github.com/cumulus13/pathlib3/blob/main/CHANGELOG.md
Keywords: pathlib,path,file,filesystem,directory,utility
Classifier: Development Status :: 5 - Production/Stable
Classifier: Intended Audience :: Developers
Classifier: Topic :: Software Development :: Libraries :: Python Modules
Classifier: Topic :: System :: Filesystems
Classifier: Programming Language :: Python :: 3
Classifier: Programming Language :: Python :: 3.6
Classifier: Programming Language :: Python :: 3.7
Classifier: Programming Language :: Python :: 3.8
Classifier: Programming Language :: Python :: 3.9
Classifier: Programming Language :: Python :: 3.10
Classifier: Programming Language :: Python :: 3.11
Classifier: Programming Language :: Python :: 3.12
Classifier: Operating System :: OS Independent
Classifier: Typing :: Typed
Requires-Python: >=3.6
Dynamic: author
Dynamic: home-page
Dynamic: requires-python
